markitdown_cli/__init__.py
markitdown_cli/cli.py
markitdown_cli-0.1.5.dist-info/licenses/LICENSE
markitdown_cli-0.1.5.dist-info/METADATA
markitdown_cli-0.1.5.dist-info/WHEEL
markitdown_cli-0.1.5.dist-info/entry_points.txt
markitdown_cli-0.1.5.dist-info/top_level.txt
markitdown_cli-0.1.5.dist-info/RECORD
