Metadata-Version: 2.4
Name: markitdown-cli
Version: 0.1.5
Summary: A CLI tool to convert a webpage to markdown
Author-email: Anes Hamdoaui <anes201ham@gmail.com>
License-Expression: MIT
Project-URL: Homepage, https://github.com/anes201/markitdown-cli
Project-URL: Bug Tracker, https://github.com/anes201/markitdown-cli/issues
Classifier: Programming Language :: Python :: 3
Classifier: Operating System :: OS Independent
Classifier: Development Status :: 4 - Beta
Classifier: Environment :: Console
Classifier: Intended Audience :: Developers
Classifier: Topic :: Text Processing :: Markup :: Markdown
Requires-Python: >=3.8
License-File: LICENSE
Requires-Dist: markitdown
Requires-Dist: requests
Requires-Dist: beautifulsoup4
Dynamic: license-file
